mmgroup/__init__.py
mmgroup/axes.py
mmgroup/bitfunctions.py
mmgroup/clifford12.cp39-win_amd64.pyd
mmgroup/conftest.py
mmgroup/generators.cp39-win_amd64.pyd
mmgroup/mat24.cp39-win_amd64.pyd
mmgroup/mm.py
mmgroup/mm127.py
mmgroup/mm15.py
mmgroup/mm255.py
mmgroup/mm3.py
mmgroup/mm31.py
mmgroup/mm7.py
mmgroup/mm_crt_space.py
mmgroup/mm_group.py
mmgroup/mm_op.cp39-win_amd64.pyd
mmgroup/mm_reduce.cp39-win_amd64.pyd
mmgroup/mm_space.py
mmgroup/mmgroup_mat24.dll
mmgroup/mmgroup_mm_op.dll
mmgroup/mmgroup_mm_reduce.dll
mmgroup/bimm/__init__.py
mmgroup/bimm/bimm.py
mmgroup/bimm/inc_p3.py
mmgroup/bimm/p3_to_mm.py
mmgroup/bimm/readme.py
mmgroup/bimm/readme_example.py
mmgroup/bimm/readme_math.py
mmgroup/demo/__init__.py
mmgroup/demo/data_types.py
mmgroup/demo/reduce_axis.py
mmgroup/demo/reduce_feasible.py
mmgroup/demo/reduce_monster.py
mmgroup/demo/reduce_sub.py
mmgroup/dev/__init__.py
mmgroup/dev/clifford12/__init__.py
mmgroup/dev/clifford12/bit64_tables.py
mmgroup/dev/clifford12/xsp2co1_doc.py
mmgroup/dev/generators/__init__.py
mmgroup/dev/generators/gen_cocode_short.py
mmgroup/dev/generators/gen_leech_22.py
mmgroup/dev/generators/gen_leech_doc.py
mmgroup/dev/generators/gen_leech_reduce_mod3.py
mmgroup/dev/generators/gen_leech_reduce_n.py
mmgroup/dev/generators/gen_random_doc.py
mmgroup/dev/generators/gen_xi_ref.py
mmgroup/dev/generators/generators_doc.py
mmgroup/dev/generators/mm_group_n_doc.py
mmgroup/dev/hadamard/__init__.py
mmgroup/dev/hadamard/hadamard_codegen.py
mmgroup/dev/hadamard/hadamard_t.py
mmgroup/dev/hadamard/hadamard_xi.py
mmgroup/dev/headers/clifford12.h
mmgroup/dev/headers/gen_ufind_lin2_aux.h
mmgroup/dev/headers/libmmgroup_mat24.lib
mmgroup/dev/headers/libmmgroup_mm_op.lib
mmgroup/dev/headers/libmmgroup_mm_reduce.lib
mmgroup/dev/headers/mat24_functions.h
mmgroup/dev/headers/mm_basics.h
mmgroup/dev/headers/mm_op_p.h
mmgroup/dev/headers/mm_op_sub.h
mmgroup/dev/headers/mm_reduce.h
mmgroup/dev/headers/mmgroup_endianess.h
mmgroup/dev/headers/mmgroup_generators.h
mmgroup-1.0.7.dist-info/METADATA
mmgroup-1.0.7.dist-info/WHEEL
mmgroup-1.0.7.dist-info/top_level.txt
mmgroup-1.0.7.dist-info/RECORD
